pltsci/__init__.py
pltsci/function.py
pltsci-0.2.2.dist-info/licenses/LICENSE
pltsci-0.2.2.dist-info/METADATA
pltsci-0.2.2.dist-info/WHEEL
pltsci-0.2.2.dist-info/top_level.txt
pltsci-0.2.2.dist-info/RECORD
