Metadata-Version: 2.4
Name: pltsci
Version: 0.2.2
Summary: A utility library for matplotlib plotting configuration
Author-email: Muxkin <muxkin@foxmail.com>
License: MIT License
Project-URL: Homepage, https://github.com/muxkin/pltsci
Project-URL: Bug Tracker, https://github.com/muxkin/pltsci/issues
Project-URL: Source Code, https://github.com/muxkin/pltsci
Keywords: matplotlib,plotting,visualization
Classifier: Development Status :: 3 - Alpha
Classifier: Intended Audience :: Developers
Classifier: License :: OSI Approved :: MIT License
Classifier: Programming Language :: Python :: 3
Classifier: Programming Language :: Python :: 3.9
Classifier: Programming Language :: Python :: 3.10
Classifier: Programming Language :: Python :: 3.11
Classifier: Programming Language :: Python :: 3.12
Classifier: Topic :: Scientific/Engineering :: Visualization
Requires-Python: >=3.9
License-File: LICENSE
Requires-Dist: matplotlib>=3.5.0
Requires-Dist: numpy>=1.20.0
Dynamic: license-file
